LICENSE
MANIFEST.in
Makefile
README.md
requirements.txt
setup.py
examples/celery_task.py
examples/redis_brpop_task.py
examples/redis_pubsub_task.py
examples/simple_task.py
examples/wait_until_done_task.py
task/__init__.py
task/task.py
task.py.egg-info/PKG-INFO
task.py.egg-info/SOURCES.txt
task.py.egg-info/dependency_links.txt
task.py.egg-info/requires.txt
task.py.egg-info/top_level.txt
task/controllers/__init__.py
task/controllers/base.py
task/controllers/redis_brpop.py
task/controllers/redis_pubsub.py
task/controllers/wait_until_done.py
tests/__init__.py
tests/mocks.py
tests/test_controllers.py
tests/test_decorators.py
tests/test_task.py