Metadata-Version: 1.0
Name: task.py
Version: 0.3
Summary: Run your task asynchronously and control/communicate with them.
Home-page: https://github.com/abhinavsingh/task.py
Author: Abhinav Singh
Author-email: mailsforabhinav@gmail.com
License: BSD
Platform: UNKNOWN
Classifier: Development Status :: 4 - Beta
Classifier: Intended Audience :: Developers
Classifier: License :: OSI Approved :: BSD License
Classifier: Operating System :: OS Independent
Classifier: Programming Language :: Python :: 2.7
Classifier: Topic :: Communications
Classifier: Topic :: Software Development :: Libraries
Classifier: Topic :: Software Development :: Libraries :: Python Modules
